translatability/__init__.py
translatability/__main__.py
translatability/io.py
translatability/translatability.py
translatability/preprocessing/__init__.py
translatability/preprocessing/extract.py
translatability/preprocessing/split.py
translatability/search/__init__.py
translatability/search/duden.py
translatability/search/google.py
translatability/tools/__init__.py
translatability/tools/command.py
translatability/tools/load.py
translatability/tools/manage.py
translatability-0.1.0.dist-info/METADATA
translatability-0.1.0.dist-info/WHEEL
translatability-0.1.0.dist-info/top_level.txt
translatability-0.1.0.dist-info/RECORD
