Metadata-Version: 2.1
Name: translatability
Version: 0.1.0
Summary: Score German noun compounds according to their English-translatability.
Home-page: https://github.com/christianj6/assessing-translatability
Author: Christian Johnson
Author-email: 
License: unlicensed
Platform: UNKNOWN
Classifier: Programming Language :: Python :: 3
Classifier: Programming Language :: Python :: 3.7
Requires-Dist: nltk (==3.6.2)
Requires-Dist: beautifulsoup4 (==4.9.3)
Requires-Dist: pyspellchecker (==0.6.2)
Requires-Dist: deep-translator (==1.5.4)
